affinidi_tdk_credential_issuance_client/__init__.py
affinidi_tdk_credential_issuance_client/api/__init__.py
affinidi_tdk_credential_issuance_client/api/configuration_api.py
affinidi_tdk_credential_issuance_client/api/credentials_api.py
affinidi_tdk_credential_issuance_client/api/default_api.py
affinidi_tdk_credential_issuance_client/api/issuance_api.py
affinidi_tdk_credential_issuance_client/api/offer_api.py
affinidi_tdk_credential_issuance_client/api/well_known_api.py
affinidi_tdk_credential_issuance_client/api_client.py
affinidi_tdk_credential_issuance_client/api_response.py
affinidi_tdk_credential_issuance_client/configuration.py
affinidi_tdk_credential_issuance_client/exceptions.py
affinidi_tdk_credential_issuance_client/models/__init__.py
affinidi_tdk_credential_issuance_client/models/action_forbidden_error.py
affinidi_tdk_credential_issuance_client/models/action_forbidden_error_details_inner.py
affinidi_tdk_credential_issuance_client/models/batch_credential_input.py
affinidi_tdk_credential_issuance_client/models/batch_credential_input_credential_requests_inner.py
affinidi_tdk_credential_issuance_client/models/batch_credential_response.py
affinidi_tdk_credential_issuance_client/models/batch_credential_response_credential_responses_inner.py
affinidi_tdk_credential_issuance_client/models/change_credential_status400_response.py
affinidi_tdk_credential_issuance_client/models/change_credential_status_input.py
affinidi_tdk_credential_issuance_client/models/change_status_forbidden_error.py
affinidi_tdk_credential_issuance_client/models/cis_configuration_webhook_setting.py
affinidi_tdk_credential_issuance_client/models/cis_configuration_webhook_setting_endpoint.py
affinidi_tdk_credential_issuance_client/models/claimed_credential_list_response.py
affinidi_tdk_credential_issuance_client/models/claimed_credential_response.py
affinidi_tdk_credential_issuance_client/models/cors_batch_credential_ok.py
affinidi_tdk_credential_issuance_client-1.65.0.dist-info/METADATA
affinidi_tdk_credential_issuance_client-1.65.0.dist-info/WHEEL
affinidi_tdk_credential_issuance_client-1.65.0.dist-info/RECORD
