Metadata-Version: 2.1
Name: affinidi_tdk_credential_issuance_client
Version: 1.65.0
Summary: CredentialIssuanceService
Home-page: https://github.com/affinidi/affinidi-tdk
License: Apache-2.0
Keywords: OpenAPI,OpenAPI-Generator,CredentialIssuanceService
Author: Affinidi
Author-email: info@affinidi.com
Requires-Python: >=3.8,<4.0
Classifier: License :: OSI Approved :: Apache Software License
Classifier: Programming Language :: Python :: 3
Classifier: Programming Language :: Python :: 3.8
Classifier: Programming Language :: Python :: 3.9
Classifier: Programming Language :: Python :: 3.10
Classifier: Programming Language :: Python :: 3.11
Classifier: Programming Language :: Python :: 3.12
Classifier: Programming Language :: Python :: 3.13
Requires-Dist: aenum (>=3.1.11)
Requires-Dist: pydantic (>=1.10.5,<2.0.0)
Requires-Dist: python-dateutil (>=2.8.2)
Requires-Dist: urllib3 (>=1.25.3)
Project-URL: Repository, https://github.com/affinidi/affinidi-tdk
